CdbApiFactory.py
setup.py
ComponentDB_API.egg-info/PKG-INFO
ComponentDB_API.egg-info/SOURCES.txt
ComponentDB_API.egg-info/dependency_links.txt
ComponentDB_API.egg-info/entry_points.txt
ComponentDB_API.egg-info/requires.txt
ComponentDB_API.egg-info/top_level.txt
cdbApi/__init__.py
cdbApi/api_client.py
cdbApi/configuration.py
cdbApi/exceptions.py
cdbApi/rest.py
cdbApi/api/__init__.py
cdbApi/api/authentication_api.py
cdbApi/api/cable_catalog_items_api.py
cdbApi/api/cable_design_items_api.py
cdbApi/api/cable_import_api.py
cdbApi/api/component_catalog_items_api.py
cdbApi/api/component_inventory_items_api.py
cdbApi/api/connector_types_api.py
cdbApi/api/domain_api.py
cdbApi/api/downloads_api.py
cdbApi/api/item_api.py
cdbApi/api/location_items_api.py
cdbApi/api/log_api.py
cdbApi/api/machine_design_items_api.py
cdbApi/api/property_type_api.py
cdbApi/api/property_value_api.py
cdbApi/api/search_api.py
cdbApi/api/sources_api.py
cdbApi/api/test_api.py
cdbApi/api/users_api.py
cdbApi/models/__init__.py
cdbApi/models/allowed_property_value.py
cdbApi/models/api_exception_message.py
cdbApi/models/api_exception_message_exception.py
cdbApi/models/api_exception_message_exception_cause.py
cdbApi/models/api_exception_message_exception_cause_stack_trace.py
cdbApi/models/api_exception_message_exception_cause_suppressed.py
cdbApi/models/cable_catalog_item_info.py
cdbApi/models/cable_design_connection_list_object.py
cdbApi/models/concise_item.py
cdbApi/models/concise_item_options.py
cdbApi/models/connector.py
cdbApi/models/connector_type.py
cdbApi/models/connector_type_id_list_request.py
cdbApi/models/control_relationship_hierarchy.py
cdbApi/models/domain.py
cdbApi/models/entity_info.py
cdbApi/models/entity_type.py
cdbApi/models/file_upload_object.py
cdbApi/models/inline_object.py
cdbApi/models/item.py
cdbApi/models/item_category.py
cdbApi/models/item_connector.py
cdbApi/models/item_domain_cable_catalog.py
cdbApi/models/item_domain_cable_catalog_all_of.py
cdbApi/models/item_domain_cable_catalog_id_list_request.py
cdbApi/models/item_domain_cable_design.py
cdbApi/models/item_domain_cable_design_all_of.py
cdbApi/models/item_domain_cable_design_id_list_request.py
cdbApi/models/item_domain_cable_inventory.py
